cppygen/__init__.py
cppygen/__main__.py
cppygen/_clang/__init__.py
cppygen/_clang/cindex.py
cppygen/_clang/enumerations.py
cppygen/cppclass.py
cppygen/cppygen_parser.py
cppygen/function.py
cppygen/logging.py
cppygen/submodule.py
cppygen/template_class.py
cppygen-0.1.8.dist-info/LICENSE
cppygen-0.1.8.dist-info/METADATA
cppygen-0.1.8.dist-info/WHEEL
cppygen-0.1.8.dist-info/entry_points.txt
cppygen-0.1.8.dist-info/RECORD
