Metadata-Version: 2.1
Name: cppygen
Version: 0.1.8
Summary: A simple c++ code generator for pybind11
Author: Gen740
Author-email: keener_slimier_0m@icloud.com
Requires-Python: >=3.10,<4.0
Classifier: Programming Language :: Python :: 3
Classifier: Programming Language :: Python :: 3.10
Classifier: Programming Language :: Python :: 3.11
Requires-Dist: colorlog (>=6.7.0,<7.0.0)
Requires-Dist: pytest (>=7.1.3,<8.0.0)
Requires-Dist: toml (>=0.10.2,<0.11.0)
